coordinated_workers/__init__.py
coordinated_workers/coordinator.py
coordinated_workers/helpers.py
coordinated_workers/models.py
coordinated_workers/nginx.py
coordinated_workers/py.typed
coordinated_workers/service_mesh.py
coordinated_workers/telemetry_correlation.py
coordinated_workers/worker.py
coordinated_workers/worker_telemetry.py
coordinated_workers/interfaces/__init__.py
coordinated_workers/interfaces/cluster.py
coordinated_workers/interfaces/py.typed
coordinated_workers-2.2.4.dist-info/METADATA
coordinated_workers-2.2.4.dist-info/WHEEL
coordinated_workers-2.2.4.dist-info/licenses/LICENSE
coordinated_workers-2.2.4.dist-info/RECORD
