Metadata-Version: 2.4
Name: coordinated-workers
Version: 2.2.4
Summary: Shared abstractions to simplify the creation and management of charms following the coordinator-worker pattern.
Project-URL: Homepage, https://github.com/canonical/cos-coordinated-workers
Project-URL: Bug Tracker, https://github.com/canonical/cos-coordinated-workers/issues
Author-email: michaeldmitry <33381599+michaeldmitry@users.noreply.github.com>
License:                                  Apache License
License-File: LICENSE
Classifier: Development Status :: 4 - Beta
Classifier: Intended Audience :: Developers
Classifier: Intended Audience :: System Administrators
Classifier: License :: OSI Approved :: Apache Software License
Classifier: Operating System :: OS Independent
Classifier: Programming Language :: Python :: 3.10
Classifier: Topic :: Utilities
Classifier: Typing :: Typed
Requires-Python: >=3.10
Requires-Dist: charmed-service-mesh-helpers>=0.2.0
Requires-Dist: cosl>=1.3.1
Requires-Dist: crossplane
Requires-Dist: cryptography
Requires-Dist: lightkube-extensions
Requires-Dist: lightkube>=v0.15.4
Requires-Dist: ops[tracing]
Requires-Dist: pydantic
